DecimalCalcul/__init__.py
DecimalCalcul/base.py
DecimalCalcul/tests/__init__.py
DecimalCalcul/tests/test_decimalBase.py
DecimalCalcul-2.4.dist-info/METADATA
DecimalCalcul-2.4.dist-info/WHEEL
DecimalCalcul-2.4.dist-info/top_level.txt
DecimalCalcul-2.4.dist-info/RECORD
