Metadata-Version: 2.1
Name: DecimalCalcul
Version: 2.4
Summary: Fournit une classe dédiée aux calculs sur des nombres décimaux
Home-page: https://github.com/bouquet-cedric/module-python
Author: Bouquet Cédric
Author-email: cedric-bouquet-7@outlook.fr
Classifier: Programming Language :: Python :: 3
Classifier: Operating System :: OS Independent
Requires-Python: >=3.0
